titanic/__init__.py
titanic/cli.py
titanic/store.py
titanic/sync.py
titanic/utils.py
titanic_sync-0.1.0.dist-info/METADATA
titanic_sync-0.1.0.dist-info/WHEEL
titanic_sync-0.1.0.dist-info/entry_points.txt
titanic_sync-0.1.0.dist-info/RECORD
