Metadata-Version: 2.3
Name: titanic-sync
Version: 0.1.0
Author-email: Dominik Cubelic <dominik.cubelic@gmail.com>
License: MIT
Requires-Python: >=3.8
Requires-Dist: click==8.1.7
Requires-Dist: pathspec>=0.12.1
Requires-Dist: rich>=13.9.3
